randomfacts/__init__.py
randomfacts/sandeep.py
randomfacts-0.1.dist-info/DESCRIPTION.rst
randomfacts-0.1.dist-info/METADATA
randomfacts-0.1.dist-info/RECORD
randomfacts-0.1.dist-info/WHEEL
randomfacts-0.1.dist-info/metadata.json
randomfacts-0.1.dist-info/top_level.txt
