Metadata-Version: 2.0
Name: randomfacts
Version: 0.1
Summary: sample package
Home-page: UNKNOWN
Author: UNKNOWN
Author-email: UNKNOWN
License: UNKNOWN
Platform: UNKNOWN
